mercury/__init__.py
mercury/client.py
mercury_fil-0.1.4.dist-info/METADATA
mercury_fil-0.1.4.dist-info/WHEEL
mercury_fil-0.1.4.dist-info/RECORD
