Metadata-Version: 2.1
Name: mercury-fil
Version: 0.1.4
Summary: Python client for accessing Filecoin chain data.
License: MIT, Apache-2.0
Keywords: filecoin,bigquery
Author: Steph Samson
Author-email: ayo@kasteph.com
Requires-Python: >=3.9,<4.0
Classifier: License :: Other/Proprietary License
Classifier: Programming Language :: Python :: 3
Classifier: Programming Language :: Python :: 3.9
Classifier: Programming Language :: Python :: 3.10
Classifier: Programming Language :: Python :: 3.11
Requires-Dist: google-auth (>=2.22.0,<3.0.0)
Requires-Dist: google-cloud-bigquery (>=3.11.4,<4.0.0)
Requires-Dist: pandas (>=2.0.3,<3.0.0)
Requires-Dist: pandas-gbq (>=0.19.2,<0.20.0)
